jobmon/core/__init__.py
jobmon/core/cli.py
jobmon/core/cluster.py
jobmon/core/cluster_protocol.py
jobmon/core/cluster_type.py
jobmon/core/configuration.py
jobmon/core/constants.py
jobmon/core/defaults.yaml
jobmon/core/exceptions.py
jobmon/core/jobmon_utils.py
jobmon/core/otlp.py
jobmon/core/py.typed
jobmon/core/requester.py
jobmon/core/serializers.py
jobmon/core/task_generator.py
jobmon/distributor/__init__.py
jobmon/distributor/api.py
jobmon/distributor/cli.py
jobmon/distributor/distributor_command.py
jobmon/distributor/distributor_service.py
jobmon/distributor/distributor_task_instance.py
jobmon/distributor/distributor_workflow_run.py
jobmon/distributor/py.typed
jobmon/distributor/task_instance_batch.py
jobmon/plugins/dummy/__init__.py
jobmon/plugins/dummy/dummy_distributor.py
jobmon/plugins/dummy/dummy_queue.py
jobmon/plugins/dummy/py.typed
jobmon/plugins/multiprocess/__init__.py
jobmon/plugins/multiprocess/multiproc_distributor.py
jobmon/plugins/multiprocess/multiproc_queue.py
jobmon/plugins/multiprocess/py.typed
jobmon/plugins/sequential/__init__.py
jobmon/plugins/sequential/py.typed
jobmon/plugins/sequential/seq_distributor.py
jobmon/plugins/sequential/seq_queue.py
jobmon/worker_node/__init__.py
jobmon/worker_node/cli.py
jobmon/worker_node/py.typed
jobmon/worker_node/worker_node_factory.py
jobmon/worker_node/worker_node_task_instance.py
jobmon_core-3.4.8.dist-info/licenses/LICENSE
jobmon_core-3.4.8.dist-info/METADATA
jobmon_core-3.4.8.dist-info/WHEEL
jobmon_core-3.4.8.dist-info/entry_points.txt
jobmon_core-3.4.8.dist-info/top_level.txt
jobmon_core-3.4.8.dist-info/RECORD
