Metadata-Version: 2.4
Name: jobmon_core
Version: 3.4.8
Summary: Shared functionality for Jobmon Namespace Packages
Classifier: Programming Language :: Python :: 3.9
Classifier: Programming Language :: Python :: 3.10
Classifier: Programming Language :: Python :: 3.11
Classifier: Programming Language :: Python :: 3.12
Requires-Python: >=3.9
License-File: LICENSE
Requires-Dist: aiohttp
Requires-Dist: pyyaml
Requires-Dist: psutil
Requires-Dist: requests
Requires-Dist: tenacity>=8.1
Requires-Dist: docstring-parser
Requires-Dist: grpcio<=1.64.1
Requires-Dist: docutils
Requires-Dist: sphinx
Requires-Dist: python-dotenv
Provides-Extra: otlp
Requires-Dist: opentelemetry-api; extra == "otlp"
Requires-Dist: opentelemetry-sdk; extra == "otlp"
Requires-Dist: opentelemetry-instrumentation; extra == "otlp"
Requires-Dist: opentelemetry-instrumentation-fastapi; extra == "otlp"
Requires-Dist: opentelemetry-instrumentation-requests; extra == "otlp"
Requires-Dist: opentelemetry-exporter-otlp; extra == "otlp"
Dynamic: license-file
